{"802311464598705038":{"listingid":"802311464598705038","price":1131,"fee":169,"publisher_fee_app":730,"publisher_fee_percent":"0.100000001490116119","currencyid":2006,"steam_fee":56,"publisher_fee":113,"converted_price":12359,"converted_fee":1852,"converted_currencyid":2018,"converted_steam_fee":617,"converted_publisher_fee":1235,"converted_price_per_unit":12359,"converted_fee_per_unit":1852,"converted_steam_fee_per_unit":617,"converted_publisher_fee_per_unit":1235,"asset":{"currency":0,"appid":730,"contextid":"2","id":"43242904892","amount":"1","market_actions":[{"link":"steam://rungame/730/76561202255233023/+csgo_econ_action_preview%20M%listingid%A%assetid%D9289838348587815824","name":"Inspect in Game..."}]}},"646937277806544095":{"listingid":"646937277806544095","price":2164,"fee":324,"publisher_fee_app":730,"publisher_fee_percent":"0.100000001490116119","currencyid":2023,"steam_fee":108,"publisher_fee":216,"converted_price":12410,"converted_fee":1861,"converted_currencyid":2018,"converted_steam_fee":620,"converted_publisher_fee":1241,"converted_price_per_unit":12410,"converted_fee_per_unit":1861,"converted_steam_fee_per_unit":620,"converted_publisher_fee_per_unit":1241,"asset":{"currency":0,"appid":730,"contextid":"2","id":"42926242926","amount":"1","market_actions":[{"link":"steam://rungame/730/76561202255233023/+csgo_econ_action_preview%20M%listingid%A%assetid%D4794797193202954684","name":"Inspect in Game..."}]}},"822577662915296566":{"listingid":"822577662915296566","price":156175,"fee":23425,"publisher_fee_app":730,"publisher_fee_percent":"0.100000001490116119","currencyid":2037,"steam_fee":7808,"publisher_fee":15617,"converted_price":12471,"converted_fee":1870,"converted_currencyid":2018,"converted_steam_fee":623,"converted_publisher_fee":1247,"converted_price_per_unit":12471,"converted_fee_per_unit":1870,"converted_steam_fee_per_unit":623,"converted_publisher_fee_per_unit":1247,"asset":{"currency":0,"appid":730,"contextid":"2","id":"43239149360","amount":"1","market_actions":[{"link":"steam://rungame/730/76561202255233023/+csgo_econ_action_preview%20M%listingid%A%assetid%D9289838348587815824","name":"Inspect in Game..."}]}},"822577662915295066":{"listingid":"822577662915295066","price":156175,"fee":23425,"publisher_fee_app":730,"publisher_fee_percent":"0.100000001490116119","currencyid":2037,"steam_fee":7808,"publisher_fee":15617,"converted_price":12471,"converted_fee":1870,"converted_currencyid":2018,"converted_steam_fee":623,"converted_publisher_fee":1247,"converted_price_per_unit":12471,"converted_fee_per_unit":1870,"converted_steam_fee_per_unit":623,"converted_publisher_fee_per_unit":1247,"asset":{"currency":0,"appid":730,"contextid":"2","id":"43239151603","amount":"1","market_actions":[{"link":"steam://rungame/730/76561202255233023/+csgo_econ_action_preview%20M%listingid%A%assetid%D9289838348587815824","name":"Inspect in Game..."}]}},"822577662915295426":{"listingid":"822577662915295426","price":156175,"fee":23425,"publisher_fee_app":730,"publisher_fee_percent":"0.100000001490116119","currencyid":2037,"steam_fee":7808,"publisher_fee":15617,"converted_price":12471,"converted_fee":1870,"converted_currencyid":2018,"converted_steam_fee":623,"converted_publisher_fee":1247,"converted_price_per_unit":12471,"converted_fee_per_unit":1870,"converted_steam_fee_per_unit":623,"converted_publisher_fee_per_unit":1247,"asset":{"currency":0,"appid":730,"contextid":"2","id":"43239150911","amount":"1","market_actions":[{"link":"steam://rungame/730/76561202255233023/+csgo_econ_action_preview%20M%listingid%A%assetid%D9289838348587815824","name":"Inspect in Game..."}]}},"822577662915295636":{"listingid":"822577662915295636","price":156175,"fee":23425,"publisher_fee_app":730,"publisher_fee_percent":"0.100000001490116119","currencyid":2037,"steam_fee":7808,"publisher_fee":15617,"converted_price":12471,"converted_fee":1870,"converted_currencyid":2018,"converted_steam_fee":623,"converted_publisher_fee":1247,"converted_price_per_unit":12471,"converted_fee_per_unit":1870,"converted_steam_fee_per_unit":623,"converted_publisher_fee_per_unit":1247,"asset":{"currency":0,"appid":730,"contextid":"2","id":"43239150114","amount":"1","market_actions":[{"link":"steam://rungame/730/76561202255233023/+csgo_econ_action_preview%20M%listingid%A%assetid%D4794797193202954684","name":"Inspect in Game..."}]}},"822577662915296746":{"listingid":"822577662915296746","price":156175,"fee":23425,"publisher_fee_app":730,"publisher_fee_percent":"0.100000001490116119","currencyid":2037,"steam_fee":7808,"publisher_fee":15617,"converted_price":12471,"converted_fee":1870,"converted_currencyid":2018,"converted_steam_fee":623,"converted_publisher_fee":1247,"converted_price_per_unit":12471,"converted_fee_per_unit":1870,"converted_steam_fee_per_unit":623,"converted_publisher_fee_per_unit":1247,"asset":{"currency":0,"appid":730,"contextid":"2","id":"43239148424","amount":"1","market_actions":[{"link":"steam://rungame/730/76561202255233023/+csgo_econ_action_preview%20M%listingid%A%assetid%D9289838348587815824","name":"Inspect in Game..."}]}},"822577662915297166":{"listingid":"822577662915297166","price":156175,"fee":23425,"publisher_fee_app":730,"publisher_fee_percent":"0.100000001490116119","currencyid":2037,"steam_fee":7808,"publisher_fee":15617,"converted_price":12471,"converted_fee":1870,"converted_currencyid":2018,"converted_steam_fee":623,"converted_publisher_fee":1247,"converted_price_per_unit":12471,"converted_fee_per_unit":1870,"converted_steam_fee_per_unit":623,"converted_publisher_fee_per_unit":1247,"asset":{"currency":0,"appid":730,"contextid":"2","id":"43239147652","amount":"1","market_actions":[{"link":"steam://rungame/730/76561202255233023/+csgo_econ_action_preview%20M%listingid%A%assetid%D9289838348587815824","name":"Inspect in Game..."}]}},"639055265211613416":{"listingid":"639055265211613416","price":25702,"fee":3855,"publisher_fee_app":730,"publisher_fee_percent":"0.100000001490116119","currencyid":2005,"steam_fee":1285,"publisher_fee":2570,"converted_price":12919,"converted_fee":1936,"converted_currencyid":2018,"converted_steam_fee":645,"converted_publisher_fee":1291,"converted_price_per_unit":12919,"converted_fee_per_unit":1936,"converted_steam_fee_per_unit":645,"converted_publisher_fee_per_unit":1291,"asset":{"currency":0,"appid":730,"contextid":"2","id":"42514855207","amount":"1","market_actions":[{"link":"steam://rungame/730/76561202255233023/+csgo_econ_action_preview%20M%listingid%A%assetid%D9289838348587815824","name":"Inspect in Game..."}]}},"645811377887515324":{"listingid":"645811377887515324","price":2175,"fee":325,"publisher_fee_app":730,"publisher_fee_percent":"0.100000001490116119","currencyid":2023,"steam_fee":108,"publisher_fee":217,"converted_price":12473,"converted_fee":1870,"converted_currencyid":2018,"converted_steam_fee":623,"converted_publisher_fee":1247,"converted_price_per_unit":12473,"converted_fee_per_unit":1870,"converted_steam_fee_per_unit":623,"converted_publisher_fee_per_unit":1247,"asset":{"currency":0,"appid":730,"contextid":"2","id":"43166408416","amount":"1","market_actions":[{"link":"steam://rungame/730/76561202255233023/+csgo_econ_action_preview%20M%listingid%A%assetid%D4794797193202954684","name":"Inspect in Game..."}]}}}