{"615412080444227360":{"listingid":"615412080444227360","price":436,"fee":64,"publisher_fee_app":730,"publisher_fee_percent":"0.100000001490116119","currencyid":2003,"steam_fee":21,"publisher_fee":43,"converted_price":20392,"converted_fee":3058,"converted_currencyid":2018,"converted_steam_fee":1019,"converted_publisher_fee":2039,"converted_price_per_unit":20392,"converted_fee_per_unit":3058,"converted_steam_fee_per_unit":1019,"converted_publisher_fee_per_unit":2039,"asset":{"currency":0,"appid":730,"contextid":"2","id":"6397657304","amount":"1","market_actions":[{"link":"steam://rungame/730/76561202255233023/+csgo_econ_action_preview%20M%listingid%A%assetid%D11674495900287446677","name":"Inspect in Game..."}]}},"535473186692899855":{"listingid":"535473186692899855","price":41653,"fee":6247,"publisher_fee_app":730,"publisher_fee_percent":"0.100000001490116119","currencyid":2005,"steam_fee":2082,"publisher_fee":4165,"converted_price":20936,"converted_fee":3139,"converted_currencyid":2018,"converted_steam_fee":1046,"converted_publisher_fee":2093,"converted_price_per_unit":20936,"converted_fee_per_unit":3139,"converted_steam_fee_per_unit":1046,"converted_publisher_fee_per_unit":2093,"asset":{"currency":0,"appid":730,"contextid":"2","id":"43295220085","amount":"1","market_actions":[{"link":"steam://rungame/730/76561202255233023/+csgo_econ_action_preview%20M%listingid%A%assetid%D11674495900287446677","name":"Inspect in Game..."}]}},"501696189839791841":{"listingid":"501696189839791841","price":43392,"fee":6508,"publisher_fee_app":730,"publisher_fee_percent":"0.100000001490116119","currencyid":2005,"steam_fee":2169,"publisher_fee":4339,"converted_price":21810,"converted_fee":3271,"converted_currencyid":2018,"converted_steam_fee":1090,"converted_publisher_fee":2181,"converted_price_per_unit":21810,"converted_fee_per_unit":3271,"converted_steam_fee_per_unit":1090,"converted_publisher_fee_per_unit":2181,"asset":{"currency":0,"appid":730,"contextid":"2","id":"43264833586","amount":"1","market_actions":[{"link":"steam://rungame/730/76561202255233023/+csgo_econ_action_preview%20M%listingid%A%assetid%D11674495900287446677","name":"Inspect in Game..."}]}},"606404880809370730":{"listingid":"606404880809370730","price":522,"fee":78,"publisher_fee_app":730,"publisher_fee_percent":"0.100000001490116119","currencyid":2001,"steam_fee":26,"publisher_fee":52,"converted_price":21600,"converted_fee":3240,"converted_currencyid":2018,"converted_steam_fee":1080,"converted_publisher_fee":2160,"converted_price_per_unit":21600,"converted_fee_per_unit":3240,"converted_steam_fee_per_unit":1080,"converted_publisher_fee_per_unit":2160,"asset":{"currency":0,"appid":730,"contextid":"2","id":"43257230276","amount":"1","market_actions":[{"link":"steam://rungame/730/76561202255233023/+csgo_econ_action_preview%20M%listingid%A%assetid%D11674495900287446677","name":"Inspect in Game..."}]}},"653692597625017664":{"listingid":"653692597625017664","price":46870,"fee":7030,"publisher_fee_app":730,"publisher_fee_percent":"0.100000001490116119","currencyid":2005,"steam_fee":2343,"publisher_fee":4687,"converted_price":23558,"converted_fee":3532,"converted_currencyid":2018,"converted_steam_fee":1177,"converted_publisher_fee":2355,"converted_price_per_unit":23558,"converted_fee_per_unit":3532,"converted_steam_fee_per_unit":1177,"converted_publisher_fee_per_unit":2355,"asset":{"currency":0,"appid":730,"contextid":"2","id":"42851083436","amount":"1","market_actions":[{"link":"steam://rungame/730/76561202255233023/+csgo_econ_action_preview%20M%listingid%A%assetid%D11674495900287446677","name":"Inspect in Game..."}]}},"663825696772547552":{"listingid":"663825696772547552","price":3939,"fee":589,"publisher_fee_app":730,"publisher_fee_percent":"0.100000001490116119","currencyid":2023,"steam_fee":196,"publisher_fee":393,"converted_price":22588,"converted_fee":3387,"converted_currencyid":2018,"converted_steam_fee":1129,"converted_publisher_fee":2258,"converted_price_per_unit":22588,"converted_fee_per_unit":3387,"converted_steam_fee_per_unit":1129,"converted_publisher_fee_per_unit":2258,"asset":{"currency":0,"appid":730,"contextid":"2","id":"42950094255","amount":"1","market_actions":[{"link":"steam://rungame/730/76561202255233023/+csgo_econ_action_preview%20M%listingid%A%assetid%D12262739559154419377","name":"Inspect in Game..."}]}},"616537980327321531":{"listingid":"616537980327321531","price":480,"fee":72,"publisher_fee_app":730,"publisher_fee_percent":"0.100000001490116119","currencyid":2003,"steam_fee":24,"publisher_fee":48,"converted_price":22450,"converted_fee":3367,"converted_currencyid":2018,"converted_steam_fee":1122,"converted_publisher_fee":2245,"converted_price_per_unit":22450,"converted_fee_per_unit":3367,"converted_steam_fee_per_unit":1122,"converted_publisher_fee_per_unit":2245,"asset":{"currency":0,"appid":730,"contextid":"2","id":"6362855393","amount":"1","market_actions":[{"link":"steam://rungame/730/76561202255233023/+csgo_econ_action_preview%20M%listingid%A%assetid%D11674495900287446677","name":"Inspect in Game..."}]}},"636804099006555771":{"listingid":"636804099006555771","price":500,"fee":75,"publisher_fee_app":730,"publisher_fee_percent":"0.100000001490116119","currencyid":2003,"steam_fee":25,"publisher_fee":50,"converted_price":23385,"converted_fee":3507,"converted_currencyid":2018,"converted_steam_fee":1169,"converted_publisher_fee":2338,"converted_price_per_unit":23385,"converted_fee_per_unit":3507,"converted_steam_fee_per_unit":1169,"converted_publisher_fee_per_unit":2338,"asset":{"currency":0,"appid":730,"contextid":"2","id":"31444440792","amount":"1","market_actions":[{"link":"steam://rungame/730/76561202255233023/+csgo_econ_action_preview%20M%listingid%A%assetid%D11674495900287446677","name":"Inspect in Game..."}]}},"650314897890440772":{"listingid":"650314897890440772","price":3958,"fee":592,"publisher_fee_app":730,"publisher_fee_percent":"0.100000001490116119","currencyid":2023,"steam_fee":197,"publisher_fee":395,"converted_price":22697,"converted_fee":3403,"converted_currencyid":2018,"converted_steam_fee":1134,"converted_publisher_fee":2269,"converted_price_per_unit":22697,"converted_fee_per_unit":3403,"converted_steam_fee_per_unit":1134,"converted_publisher_fee_per_unit":2269,"asset":{"currency":0,"appid":730,"contextid":"2","id":"42951038781","amount":"1","market_actions":[{"link":"steam://rungame/730/76561202255233023/+csgo_econ_action_preview%20M%listingid%A%assetid%D12262739559154419377","name":"Inspect in Game..."}]}},"508451589273434143":{"listingid":"508451589273434143","price":2088,"fee":312,"publisher_fee_app":730,"publisher_fee_percent":"0.100000001490116119","currencyid":2006,"steam_fee":104,"publisher_fee":208,"converted_price":22815,"converted_fee":3421,"converted_currencyid":2018,"converted_steam_fee":1140,"converted_publisher_fee":2281,"converted_price_per_unit":22815,"converted_fee_per_unit":3421,"converted_steam_fee_per_unit":1140,"converted_publisher_fee_per_unit":2281,"asset":{"currency":0,"appid":730,"contextid":"2","id":"29517319952","amount":"1","market_actions":[{"link":"steam://rungame/730/76561202255233023/+csgo_econ_action_preview%20M%listingid%A%assetid%D12271964187898929685","name":"Inspect in Game..."}]}}}